quiet/__init__.py
quiet/web_ui.py
quiet/htdocs/quiet.css
quiet/htdocs/quiet.js
quiet/htdocs/quiet.png
TracQuiet-1.2.1.dist-info/COPYING
TracQuiet-1.2.1.dist-info/METADATA
TracQuiet-1.2.1.dist-info/WHEEL
TracQuiet-1.2.1.dist-info/entry_points.txt
TracQuiet-1.2.1.dist-info/top_level.txt
TracQuiet-1.2.1.dist-info/RECORD
