Metadata-Version: 2.1
Name: TracQuiet
Version: 1.2.1
Summary: Toggles quiet (no email) mode for Trac notifications
Home-page: https://trac-hacks.org/wiki/QuietPlugin
Author: Rob Guttman
Author-email: guttman@alum.mit.edu
License: 3-Clause BSD
Platform: UNKNOWN
Classifier: Framework :: Trac
Requires-Dist: Trac
